alooma_pysdk/__init__.py
alooma_pysdk/alooma_ca
alooma_pysdk/alooma_pysdk.py
alooma_pysdk/consts.py
alooma_pysdk/py2to3.py
alooma_pysdk/pysdk_exceptions.py
alooma_pysdk-2.1.dist-info/LICENSE
alooma_pysdk-2.1.dist-info/METADATA
alooma_pysdk-2.1.dist-info/WHEEL
alooma_pysdk-2.1.dist-info/top_level.txt
alooma_pysdk-2.1.dist-info/RECORD
